{
  "unversionedId": "tutorial-extras/canisters-code",
  "id": "tutorial-extras/canisters-code",
  "isDocsHomePage": false,
  "title": "程序罐(容器)和代码",
  "description": "程序罐(容器)和代码",
  "source": "@site/docs/tutorial-extras/canisters-code.md",
  "sourceDirName": "tutorial-extras",
  "slug": "/tutorial-extras/canisters-code",
  "permalink": "/docs/tutorial-extras/canisters-code",
  "editUrl": "https://github.com/NnsDao/dfinity-sdk-docs/edit/main/docs/tutorial-extras/canisters-code.md",
  "version": "current",
  "sidebarPosition": 5,
  "frontMatter": {
    "sidebar_position": 5
  },
  "sidebar": "tutorialSidebar",
  "previous": {
    "title": "去中心化数据中心",
    "permalink": "/docs/tutorial-extras/data-centers"
  },
  "next": {
    "title": "通证和cycles燃料",
    "permalink": "/docs/tutorial-extras/tokens-cycles"
  }
}